Metadata-Version: 2.1
Name: zssfunniest
Version: 0.1.2
Summary: The funniest joke in the world
Home-page: http://github.com/storborg/funniest
Author: zheng ss
Author-email: szheng@example.com
License: MIT
